pixel_client/__init__.py
pixel_client/_base.py
pixel_client/_sync.py
pixel_client/auth.py
pixel_client/exceptions.py
pixel_client/models.py
pixel_client/py.typed
pixel_client/settings.py
pixel_client/types.py
pixel_client/utils.py
pixel_client-1.2.5.dist-info/METADATA
pixel_client-1.2.5.dist-info/WHEEL
pixel_client-1.2.5.dist-info/licenses/LICENSE.txt
pixel_client-1.2.5.dist-info/RECORD
