Metadata-Version: 2.4
Name: pixel-client
Version: 1.2.5
Summary: Client library for Geodata Pixel
Project-URL: Documentation, https://doc.geodatapixel.no/
Project-URL: Organization, https://geodata.no
Author-email: "Øystein F. Skogvold" <oystein.skogvold@geodata.no>, Brede Hauge <brede.hauge@geodata.no>
Maintainer-email: "Øystein F. Skogvold" <oystein.skogvold@geodata.no>, Brede Hauge <brede.hauge@geodata.no>
License-File: LICENSE.txt
Classifier: Operating System :: OS Independent
Classifier: Programming Language :: Python :: 3
Requires-Python: >=3.11
Requires-Dist: geojson-pydantic>=1.2.0
Requires-Dist: httpx>=0.28.1
Requires-Dist: packaging>=25.0
Requires-Dist: pydantic-settings>=2.8.0
Requires-Dist: pydantic[email]>=2.10.6
Requires-Dist: tenacity>=9.1.2
Requires-Dist: tqdm>=4.67.1
